redshells/__init__.py
redshells/app/__init__.py
redshells/app/word_item_similarity/__init__.py
redshells/app/word_item_similarity/build_word_item_similarity.py
redshells/app/word_item_similarity/calculate_document_embedding.py
redshells/app/word_item_similarity/calculate_word_embedding.py
redshells/app/word_item_similarity/calculate_word_item_similarity.py
redshells/app/word_item_similarity/dimension_reduction_model.py
redshells/app/word_item_similarity/filter_item_by_word_similarity.py
redshells/app/word_item_similarity/find_item_keyword_by_matching.py
redshells/app/word_item_similarity/make_click_train_data.py
redshells/app/word_item_similarity/make_similarity_data.py
redshells/contrib/__init__.py
redshells/contrib/app/__init__.py
redshells/contrib/app/word_item_similarity/__init__.py
redshells/contrib/app/word_item_similarity/calculate_similarity_with_matrix_factorization.py
redshells/contrib/model/__init__.py
redshells/contrib/model/early_stopping.py
redshells/contrib/model/factorization_machine.py
redshells/contrib/model/feature_aggregation_similarity_model.py
redshells/contrib/model/gcmc_dataset.py
redshells/contrib/model/graph_convolutional_matrix_completion.py
redshells/contrib/model/matrix_factorization_model.py
redshells/contrib/model/utils.py
redshells/contrib/train/__init__.py
redshells/contrib/train/train_feature_aggregation_similarity_model.py
redshells/contrib/train/train_graph_convolutional_matrix_completion.py
redshells/contrib/train/train_matrix_factorization.py
redshells/data/__init__.py
redshells/data/data_frame_utils.py
redshells/data/load_data_of_task.py
redshells/data/load_existing_file.py
redshells/factory/__init__.py
redshells/factory/optuna_param_factory.py
redshells/factory/prediction_model_factory.py
redshells/factory/singleton.py
redshells/model/__init__.py
redshells/model/lda_model.py
redshells/model/scdv.py
redshells/model/tdidf.py
redshells/model/tfidf.py
redshells/model/utils.py
redshells/train/__init__.py
redshells-0.1.22.dist-info/LICENSE
redshells-0.1.22.dist-info/WHEEL
redshells-0.1.22.dist-info/METADATA
redshells-0.1.22.dist-info/RECORD
