Metadata-Version: 2.1
Name: redshells
Version: 0.1.22
Summary: Tasks which are defined using gokart.TaskOnKart. The tasks can be used with data pipeline library "luigi".
Home-page: https://github.com/m3dev/redshells
License: MIT
Author: M3, inc.
Requires-Python: >=3.7,<4.0
Classifier: License :: OSI Approved :: MIT License
Classifier: Programming Language :: Python :: 3
Classifier: Programming Language :: Python :: 3.10
Classifier: Programming Language :: Python :: 3.7
Classifier: Programming Language :: Python :: 3.8
Classifier: Programming Language :: Python :: 3.9
Requires-Dist: docutils (==0.15)
Requires-Dist: gensim (==3.8.3)
Requires-Dist: gokart (>=0.1.20)
Requires-Dist: numpy
Requires-Dist: optuna (>=0.6.0)
Requires-Dist: pandas (<1.2)
Requires-Dist: scikit-learn
Requires-Dist: scipy
Requires-Dist: tqdm
Project-URL: Repository, https://github.com/m3dev/redshells
